math_sdk/__init__.py
math_sdk/operations.py
math_smpi_sdk-0.1.1.dist-info/METADATA
math_smpi_sdk-0.1.1.dist-info/WHEEL
math_smpi_sdk-0.1.1.dist-info/top_level.txt
math_smpi_sdk-0.1.1.dist-info/RECORD
