Metadata-Version: 2.4
Name: math-smpi-sdk
Version: 0.1.1
Summary: A simple SDK for basic math operations.
Author: Shubham Kanzariya
Requires-Python: >=3.6
Dynamic: author
Dynamic: requires-python
Dynamic: summary
